automate_supervised_dataset_generation/__init__.py
automate_supervised_dataset_generation/automate.py
automate_supervised_dataset_generation-0.8.0.dist-info/METADATA
automate_supervised_dataset_generation-0.8.0.dist-info/WHEEL
automate_supervised_dataset_generation-0.8.0.dist-info/top_level.txt
automate_supervised_dataset_generation-0.8.0.dist-info/RECORD
