Metadata-Version: 2.1
Name: automate-supervised-dataset-generation
Version: 0.8.0
Summary: A brief description
Home-page: https://github.com/prakHr/automate-supervised-dataset-generation
Author: Prakhar Gandhi
Author-email: gprakhar0@gmail.com
Classifier: Programming Language :: Python :: 3
Classifier: License :: OSI Approved :: MIT License
Classifier: Operating System :: OS Independent
Requires-Python: >=3.6
Requires-Dist: mpire
Requires-Dist: playwright
Requires-Dist: transformers
Requires-Dist: torch
Requires-Dist: torchvision
Requires-Dist: hyperopt ==0.2.5
Requires-Dist: hpsklearn ==0.1.0
Requires-Dist: numpy ==1.23
Requires-Dist: languagemodels
